workflow_kit/__init__.py
workflow_kit/dependencies.py
workflow_kit/exceptions.py
workflow_kit/orchestration.py
workflow_kit/results.py
workflow_kit/router.py
workflow_kit/step.py
workflow_kit/types.py
workflow_kit/workflow.py
workflow_kit-0.1.2.dist-info/METADATA
workflow_kit-0.1.2.dist-info/WHEEL
workflow_kit-0.1.2.dist-info/licenses/LICENSE
workflow_kit-0.1.2.dist-info/RECORD
