Metadata-Version: 2.4
Name: workflow-kit
Version: 0.1.2
Summary: Lightweight library for building event-driven applications
License: MIT License
License-File: LICENSE
Classifier: License :: OSI Approved :: MIT License
Classifier: Operating System :: OS Independent
Classifier: Programming Language :: Python :: 3
Requires-Python: >=3.10
Requires-Dist: pydantic>=2.11.9
